README
setup.py
hgwin/__init__.py
hgwin/hgwin.py
hgwin/newconnectiondialog.py
hgwin/serverlist.py
hgwin/servers.py
hgwin/taskbaricon.py
hgwin.egg-info/PKG-INFO
hgwin.egg-info/SOURCES.txt
hgwin.egg-info/dependency_links.txt
hgwin.egg-info/entry_points.txt
hgwin.egg-info/requires.txt
hgwin.egg-info/top_level.txt
