Metadata-Version: 1.0
Name: hgwin
Version: 1.0d
Summary: hg serve manager for Windows using wxPython
Home-page: UNKNOWN
Author: Charles Mason, Andres Riofrio
Author-email: cemasoniv@gmail.com, andresjriofrio@gmail.com
License: UNKNOWN
Platform: UNKNOWN
Classifier: Development Status :: 3 - Alpha
